{"defaultHandlersVersion":{},"mimeTypes":{"application/pdf":{"action":3,"extensions":["pdf"]},"image/webp":{"action":3,"extensions":["webp"]},"image/avif":{"action":3,"extensions":["avif"]}},"schemes":{"mailto":{"stubEntry":true,"handlers":[null,{"name":"Gmail","uriTemplate":"https://mail.google.com/mail/?extsrc=mailto&url=%s"}]},"slack":{"action":4},"quip":{"action":4},"raycast":{"action":4},"vscode":{"action":4},"jetbrains":{"action":4},"macappstores":{"action":4},"toggltrack":{"action":4},"fb":{"action":4},"msteams":{"action":4},"zoomus":{"action":4},"macappstore":{"action":4},"acme":{"action":4},"odopen":{"action":4},"affinity":{"action":4},"chime":{"action":4},"awsquick":{"action":4}},"isDownloadsImprovementsAlreadyMigrated":false}